fracridge/__init__.py
fracridge/_linalg.py
fracridge/_numba.py
fracridge/fracridge.py
fracridge/version.py
fracridge/tests/test_fracridge.py
fracridge-2.0.dist-info/LICENSE
fracridge-2.0.dist-info/METADATA
fracridge-2.0.dist-info/WHEEL
fracridge-2.0.dist-info/top_level.txt
fracridge-2.0.dist-info/RECORD
