Metadata-Version: 2.1
Name: fracridge
Version: 2.0
Summary: Fractional Ridge Regression
Home-page: https://nrdg.github.io/fracridge
Download-URL: https://github.com/nrdg/fracridge
Author: Ariel Rokem and Kendrick Kay
Author-email: arokem@gmail.com
Maintainer: Ariel Rokem
Maintainer-email: arokem@gmail.com
License: BSD License
Platform: OS Independent
Classifier: Development Status :: 3 - Alpha
Classifier: Environment :: Console
Classifier: Intended Audience :: Science/Research
Classifier: License :: OSI Approved :: BSD License
Classifier: Operating System :: OS Independent
Classifier: Programming Language :: Python
Classifier: Topic :: Scientific/Engineering
Requires-Python: >=3.7
License-File: LICENSE
Requires-Dist: scikit-learn
Requires-Dist: numba
Requires-Dist: setuptools-scm
Requires-Dist: pillow
Provides-Extra: dev
Requires-Dist: matplotlib ; extra == 'dev'
Requires-Dist: pytest ; extra == 'dev'
Requires-Dist: pytest-cov ; extra == 'dev'
Requires-Dist: pytest-benchmark ; extra == 'dev'
Requires-Dist: sphinx ; extra == 'dev'
Requires-Dist: sphinx-gallery ; extra == 'dev'
Requires-Dist: numpydoc ; extra == 'dev'
Requires-Dist: sphinx-rtd-theme ; extra == 'dev'
Requires-Dist: sphinx-copybutton ; extra == 'dev'
Requires-Dist: sphinxcontrib-matlabdomain ; extra == 'dev'
Requires-Dist: flake8 ; extra == 'dev'
